microfaune/__init__.py
microfaune/audio.py
microfaune/data_augmentation.py
microfaune/dataaugmentation.py
microfaune/detection.py
microfaune/labeling.py
microfaune/plot.py
microfaune/data/model_weights-20190919_220113.h5
microfaune/data/model_weights_tf2-20200912_173814.h5
microfaune_ai-1.0.11603374979.dist-info/METADATA
microfaune_ai-1.0.11603374979.dist-info/WHEEL
microfaune_ai-1.0.11603374979.dist-info/top_level.txt
microfaune_ai-1.0.11603374979.dist-info/RECORD
