Metadata-Version: 2.1
Name: microfaune-ai
Version: 1.0.11603374979
Summary: Module package used for the Microfaune project
Home-page: https://github.com/microfaune/microfaune_ai
Author: Microfaune - Data For Good
Author-email: microfaune@fake.com
License: Open license
Download-URL: https://github.com/microfaune/microfaune_ai/tree/main
Platform: UNKNOWN
Classifier: Development Status :: 4 - Beta
Classifier: Environment :: Console
Classifier: Intended Audience :: Developers
Classifier: Intended Audience :: Education
Classifier: Intended Audience :: Science/Research
Classifier: License :: Free For Educational Use
Classifier: Programming Language :: Python :: 3
Classifier: Programming Language :: Python :: 3.8
Classifier: Topic :: Scientific/Engineering :: Artificial Intelligence
Classifier: Topic :: Multimedia :: Sound/Audio :: Analysis
Requires-Dist: beautifulsoup4 (==4.9.1)
Requires-Dist: keras (==2.4.3)
Requires-Dist: librosa (==0.8.0)
Requires-Dist: matplotlib (==3.3.2)
Requires-Dist: numpy (==1.18.5)
Requires-Dist: pandas (==1.1.2)
Requires-Dist: scipy (==1.4.1)
Requires-Dist: tensorflow (==2.3.0)
